{
  "entity": {
    "location": {
      "namespaceTitle": "Fuse.Triggers",
      "namespaceUri": "fuse/triggers",
      "packageName": "Fuse.Triggers",
      "packageVersion": "1.11.2"
    },
    "parameters": [
      {
        "name": "flag",
        "href": "fuse/triggers/statetransition",
        "title": "StateTransition",
        "fullyQualifiedTitle": "Fuse.Triggers.StateTransition"
      }
    ],
    "returns": {
      "href": "uno/bool",
      "title": "bool",
      "fullyQualifiedTitle": "bool"
    },
    "id": {
      "id": "fuse/triggers/statetransition/hasflag_a1832740",
      "parentId": "fuse/triggers/statetransition",
      "type": "Method",
      "modifiers": [
        "public",
        "intrinsic",
        "generated"
      ]
    },
    "uri": {
      "idUri": "fuse/triggers/statetransition/hasflag_a1832740",
      "href": "fuse/triggers/statetransition/hasflag_a1832740"
    },
    "titles": {
      "pageTitle": "StateTransition.HasFlag Method (StateTransition)",
      "navigationTitle": "HasFlag Method (StateTransition)",
      "fullTitle": "Fuse.Triggers.StateTransition.HasFlag",
      "indexTitle": "HasFlag(StateTransition)",
      "fullyQualifiedIndexTitle": "Fuse.Triggers.StateTransition.HasFlag(Fuse.Triggers.StateTransition)"
    },
    "syntax": {
      "uno": "public intrinsic generated bool HasFlag(Fuse.Triggers.StateTransition flag) {}"
    }
  },
  "tableOfContents": {}
}