{
  "entity": {
    "location": {
      "namespaceTitle": "Fuse.Controls",
      "namespaceUri": "fuse/controls",
      "packageName": "Fuse.Maps",
      "packageVersion": "2.0.0-beta.9"
    },
    "returns": {
      "href": "fuse/controls/overlaytype",
      "title": "OverlayType",
      "fullyQualifiedTitle": "Fuse.Controls.OverlayType"
    },
    "values": [
      {
        "uri": "fuse/controls/overlaytype/polyline",
        "title": "Polyline"
      },
      {
        "uri": "fuse/controls/overlaytype/polygon",
        "title": "Polygon"
      },
      {
        "uri": "fuse/controls/overlaytype/circle",
        "title": "Circle"
      }
    ],
    "id": {
      "id": "fuse/controls/overlaytype/polyline",
      "parentId": "fuse/controls/overlaytype",
      "type": "Literal",
      "modifiers": [
        "public"
      ]
    },
    "uri": {
      "idUri": "fuse/controls/overlaytype/polyline",
      "href": "fuse/controls/overlaytype/polyline"
    },
    "titles": {
      "pageTitle": "OverlayType.Polyline Literal",
      "navigationTitle": "Polyline Literal",
      "fullTitle": "Fuse.Controls.OverlayType.Polyline",
      "indexTitle": "Polyline",
      "fullyQualifiedIndexTitle": "Fuse.Controls.OverlayType.Polyline"
    },
    "syntax": {
      "uno": "public Fuse.Controls.OverlayType Polyline;"
    }
  },
  "tableOfContents": {}
}