{
  "entity": {
    "location": {
      "namespaceTitle": "Uno.IO",
      "namespaceUri": "uno/io",
      "packageName": "UnoCore",
      "packageVersion": "1.11.1"
    },
    "returns": {
      "href": "uno/io/seekorigin",
      "title": "SeekOrigin",
      "fullyQualifiedTitle": "Uno.IO.SeekOrigin"
    },
    "values": [
      {
        "uri": "uno/io/seekorigin/begin",
        "title": "Begin"
      },
      {
        "uri": "uno/io/seekorigin/current",
        "title": "Current"
      },
      {
        "uri": "uno/io/seekorigin/end",
        "title": "End"
      }
    ],
    "id": {
      "id": "uno/io/seekorigin/end",
      "parentId": "uno/io/seekorigin",
      "type": "Literal",
      "modifiers": [
        "public"
      ]
    },
    "uri": {
      "idUri": "uno/io/seekorigin/end",
      "href": "uno/io/seekorigin/end"
    },
    "titles": {
      "pageTitle": "SeekOrigin.End Literal",
      "navigationTitle": "End Literal",
      "fullTitle": "Uno.IO.SeekOrigin.End",
      "indexTitle": "End",
      "fullyQualifiedIndexTitle": "Uno.IO.SeekOrigin.End"
    },
    "syntax": {
      "uno": "public Uno.IO.SeekOrigin End;"
    }
  },
  "tableOfContents": {}
}