{
  "entity": {
    "location": {
      "namespaceTitle": "Fuse.Controls",
      "namespaceUri": "fuse/controls",
      "packageName": "Fuse.Controls.Primitives",
      "packageVersion": "1.11.2"
    },
    "parameters": [],
    "returns": {
      "href": "fuse/drawing/brush",
      "title": "Brush",
      "fullyQualifiedTitle": "Fuse.Drawing.Brush"
    },
    "uxProperties": {},
    "id": {
      "id": "fuse/controls/shape/fill",
      "parentId": "fuse/controls/shape",
      "type": "UxProperty",
      "modifiers": [
        "public"
      ]
    },
    "uri": {
      "idUri": "fuse/controls/shape/fill",
      "href": "fuse/controls/shape/fill"
    },
    "titles": {
      "pageTitle": "Shape.Fill Property",
      "navigationTitle": "Fill Property",
      "fullTitle": "Fuse.Controls.Shape.Fill",
      "indexTitle": "Fill",
      "fullyQualifiedIndexTitle": "Fuse.Controls.Shape.Fill"
    },
    "syntax": {
      "uno": "public Fuse.Drawing.Brush Fill { get; get; }"
    },
    "comment": {
      "brief": "The `Fill` property sets a single fill on the `Shape`",
      "full": "The `Fill` property sets a single fill on the `Shape`"
    }
  },
  "tableOfContents": {}
}