{
  "entity": {
    "location": {
      "namespaceTitle": "Fuse.Elements",
      "namespaceUri": "fuse/elements",
      "packageName": "Fuse.Elements",
      "packageVersion": "1.11.2"
    },
    "returns": {
      "href": "fuse/elements/stretchdirection",
      "title": "StretchDirection",
      "fullyQualifiedTitle": "Fuse.Elements.StretchDirection"
    },
    "values": [
      {
        "uri": "fuse/elements/stretchdirection/both",
        "title": "Both",
        "comment": {
          "brief": "An image can be stretched both larger and smaller.",
          "full": "An image can be stretched both larger and smaller."
        }
      },
      {
        "uri": "fuse/elements/stretchdirection/uponly",
        "title": "UpOnly",
        "comment": {
          "brief": "An image will only be expanded to fill up available space, it will not shrink.",
          "full": "An image will only be expanded to fill up available space, it will not shrink."
        }
      },
      {
        "uri": "fuse/elements/stretchdirection/downonly",
        "title": "DownOnly",
        "comment": {
          "brief": "An image will only be shrunk to fit in the available space, it will not expand.",
          "full": "An image will only be shrunk to fit in the available space, it will not expand."
        }
      }
    ],
    "id": {
      "id": "fuse/elements/stretchdirection/uponly",
      "parentId": "fuse/elements/stretchdirection",
      "type": "Literal",
      "modifiers": [
        "public"
      ]
    },
    "uri": {
      "idUri": "fuse/elements/stretchdirection/uponly",
      "href": "fuse/elements/stretchdirection/uponly"
    },
    "titles": {
      "pageTitle": "StretchDirection.UpOnly Literal",
      "navigationTitle": "UpOnly Literal",
      "fullTitle": "Fuse.Elements.StretchDirection.UpOnly",
      "indexTitle": "UpOnly",
      "fullyQualifiedIndexTitle": "Fuse.Elements.StretchDirection.UpOnly"
    },
    "syntax": {
      "uno": "public Fuse.Elements.StretchDirection UpOnly;"
    },
    "comment": {
      "brief": "An image will only be expanded to fill up available space, it will not shrink.",
      "full": "An image will only be expanded to fill up available space, it will not shrink."
    }
  },
  "tableOfContents": {}
}