{
  "entity": {
    "location": {
      "namespaceTitle": "Fuse",
      "namespaceUri": "fuse",
      "packageName": "Fuse.Common",
      "packageVersion": "1.11.2"
    },
    "parameters": [
      {
        "name": "d",
        "href": "fuse/diagnostic",
        "title": "Diagnostic",
        "fullyQualifiedTitle": "Fuse.Diagnostic"
      }
    ],
    "id": {
      "id": "fuse/diagnostics/report_64903dec",
      "parentId": "fuse/diagnostics",
      "type": "Method",
      "modifiers": [
        "public",
        "static"
      ]
    },
    "uri": {
      "idUri": "fuse/diagnostics/report_64903dec",
      "href": "fuse/diagnostics/report_64903dec"
    },
    "titles": {
      "pageTitle": "Diagnostics.Report Method (Diagnostic)",
      "navigationTitle": "Report Method (Diagnostic)",
      "fullTitle": "Fuse.Diagnostics.Report",
      "indexTitle": "Report(Diagnostic)",
      "fullyQualifiedIndexTitle": "Fuse.Diagnostics.Report(Fuse.Diagnostic)"
    },
    "syntax": {
      "uno": "public static voidReport(Fuse.Diagnostic d) {}"
    }
  },
  "tableOfContents": {}
}