{
  "entity": {
    "location": {
      "namespaceTitle": "Fuse.Reactive",
      "namespaceUri": "fuse/reactive",
      "packageName": "Fuse.Reactive.Bindings",
      "packageVersion": "1.11.2"
    },
    "parameters": [
      {
        "name": "left",
        "href": "fuse/reactive/instancedefaults",
        "title": "InstanceDefaults",
        "fullyQualifiedTitle": "Fuse.Reactive.InstanceDefaults"
      },
      {
        "name": "right",
        "href": "fuse/reactive/instancedefaults",
        "title": "InstanceDefaults",
        "fullyQualifiedTitle": "Fuse.Reactive.InstanceDefaults"
      }
    ],
    "returns": {
      "href": "uno/bool",
      "title": "bool",
      "fullyQualifiedTitle": "bool"
    },
    "id": {
      "id": "fuse/reactive/instancedefaults/op_equality_f15f73a2",
      "parentId": "fuse/reactive/instancedefaults",
      "type": "Operator",
      "modifiers": [
        "public",
        "intrinsic",
        "static",
        "generated"
      ]
    },
    "uri": {
      "idUri": "fuse/reactive/instancedefaults/op_equality_f15f73a2",
      "href": "fuse/reactive/instancedefaults/op_equality_f15f73a2"
    },
    "titles": {
      "pageTitle": "InstanceDefaults == InstanceDefaults Operator",
      "navigationTitle": "InstanceDefaults == InstanceDefaults Operator",
      "fullTitle": "Fuse.Reactive.InstanceDefaults.op_Equality",
      "indexTitle": "InstanceDefaults == InstanceDefaults",
      "fullyQualifiedIndexTitle": "Fuse.Reactive.InstanceDefaults.InstanceDefaults == InstanceDefaults"
    },
    "syntax": {
      "uno": "public intrinsic static generated bool op_Equality(Fuse.Reactive.InstanceDefaults left, Fuse.Reactive.InstanceDefaults right) {}"
    }
  },
  "tableOfContents": {}
}