{
  "entity": {
    "location": {
      "namespaceTitle": "Uno",
      "namespaceUri": "uno",
      "packageName": "UnoCore",
      "packageVersion": "1.11.1"
    },
    "parameters": [
      {
        "name": "radians",
        "href": "uno/float4",
        "title": "float4",
        "fullyQualifiedTitle": "float4"
      }
    ],
    "returns": {
      "href": "uno/float4",
      "title": "float4",
      "fullyQualifiedTitle": "float4"
    },
    "attributes": [
      {
        "parameters": [
          "asin"
        ],
        "id": {
          "id": "uno/compiler/exporttargetinterop/glslintrinsicattribute",
          "parentId": "uno/compiler/exporttargetinterop",
          "type": "Class",
          "modifiers": [
            "public",
            "sealed"
          ]
        },
        "uri": {
          "idUri": "uno/compiler/exporttargetinterop/glslintrinsicattribute",
          "href": "uno/compiler/exporttargetinterop/glslintrinsicattribute"
        },
        "titles": {
          "indexTitle": "GlslIntrinsicAttribute",
          "fullyQualifiedIndexTitle": "Uno.Compiler.ExportTargetInterop.GlslIntrinsicAttribute"
        }
      }
    ],
    "id": {
      "id": "uno/math/asin_7b2bf2a2",
      "parentId": "uno/math",
      "type": "Method",
      "modifiers": [
        "public",
        "static"
      ]
    },
    "uri": {
      "idUri": "uno/math/asin_7b2bf2a2",
      "href": "uno/math/asin_7b2bf2a2"
    },
    "titles": {
      "pageTitle": "Math.Asin Method (float4)",
      "navigationTitle": "Asin Method (float4)",
      "fullTitle": "Uno.Math.Asin",
      "indexTitle": "Asin(float4)",
      "fullyQualifiedIndexTitle": "Uno.Math.Asin(float4)"
    },
    "syntax": {
      "uno": "[Uno.Compiler.ExportTargetInterop.GlslIntrinsic(name = \"asin\")]\npublic static float4 Asin(float4 radians) {}"
    }
  },
  "tableOfContents": {}
}