{
  "entity": {
    "location": {
      "namespaceTitle": "Uno.Diagnostics",
      "namespaceUri": "uno/diagnostics",
      "packageName": "UnoCore",
      "packageVersion": "1.11.1"
    },
    "parameters": [
      {
        "name": "message",
        "href": "uno/object",
        "title": "object",
        "fullyQualifiedTitle": "object"
      },
      {
        "name": "type",
        "href": "uno/diagnostics/debugmessagetype",
        "title": "DebugMessageType",
        "fullyQualifiedTitle": "Uno.Diagnostics.DebugMessageType"
      }
    ],
    "id": {
      "id": "uno/diagnostics/debug/log_edba99a3",
      "parentId": "uno/diagnostics/debug",
      "type": "Method",
      "modifiers": [
        "public",
        "static"
      ]
    },
    "uri": {
      "idUri": "uno/diagnostics/debug/log_edba99a3",
      "href": "uno/diagnostics/debug/log_edba99a3"
    },
    "titles": {
      "pageTitle": "Debug.Log Method (object, DebugMessageType)",
      "navigationTitle": "Log Method (object, DebugMessageType)",
      "fullTitle": "Uno.Diagnostics.Debug.Log",
      "indexTitle": "Log(object, DebugMessageType)",
      "fullyQualifiedIndexTitle": "Uno.Diagnostics.Debug.Log(object, Uno.Diagnostics.DebugMessageType)"
    },
    "syntax": {
      "uno": "public static voidLog(object message, Uno.Diagnostics.DebugMessageType type = (Uno.Diagnostics.DebugMessageType) 0) {}"
    }
  },
  "tableOfContents": {}
}