{
  "entity": {
    "location": {
      "namespaceTitle": "Fuse.Reactive.FuseJS",
      "namespaceUri": "fuse/reactive/fusejs",
      "packageName": "Fuse.Launcher.Maps",
      "packageVersion": "1.11.2"
    },
    "parameters": [],
    "id": {
      "id": "fuse/reactive/fusejs/maps/_ctor",
      "parentId": "fuse/reactive/fusejs/maps",
      "type": "Constructor",
      "modifiers": [
        "public"
      ]
    },
    "uri": {
      "idUri": "fuse/reactive/fusejs/maps/_ctor",
      "href": "fuse/reactive/fusejs/maps/_ctor"
    },
    "titles": {
      "pageTitle": "Maps Constructor",
      "navigationTitle": "Maps Constructor",
      "fullTitle": "Fuse.Reactive.FuseJS.Maps..ctor",
      "indexTitle": "Maps",
      "fullyQualifiedIndexTitle": "Fuse.Reactive.FuseJS.Maps.Maps"
    },
    "syntax": {
      "uno": "public Maps() {}"
    }
  },
  "tableOfContents": {}
}