{
  "entity": {
    "location": {
      "namespaceTitle": "Fuse.Effects",
      "namespaceUri": "fuse/effects",
      "packageName": "Fuse.Controls.Primitives",
      "packageVersion": "2.2.0"
    },
    "parameters": [],
    "returns": {
      "href": "uno/float3",
      "title": "float3",
      "fullyQualifiedTitle": "float3"
    },
    "uxProperties": {},
    "id": {
      "id": "fuse/effects/glass/lumarange",
      "parentId": "fuse/effects/glass",
      "type": "UxProperty",
      "modifiers": [
        "public"
      ]
    },
    "uri": {
      "idUri": "fuse/effects/glass/lumarange",
      "href": "fuse/effects/glass/lumarange"
    },
    "titles": {
      "pageTitle": "Glass.LumaRange Property",
      "navigationTitle": "LumaRange Property",
      "fullTitle": "Fuse.Effects.Glass.LumaRange",
      "indexTitle": "LumaRange",
      "fullyQualifiedIndexTitle": "Fuse.Effects.Glass.LumaRange"
    },
    "syntax": {
      "uno": "public float3 LumaRange { get; get; }"
    }
  },
  "tableOfContents": {}
}