{
  "entity": {
    "location": {
      "namespaceTitle": "Fuse.Controls.Native",
      "namespaceUri": "fuse/controls/native",
      "packageName": "Fuse.Controls.Native",
      "packageVersion": "1.11.2"
    },
    "parameters": [],
    "returns": {
      "href": "uno/bool",
      "title": "bool",
      "fullyQualifiedTitle": "bool"
    },
    "id": {
      "id": "fuse/controls/native/itoggleview/value",
      "parentId": "fuse/controls/native/itoggleview",
      "type": "Property",
      "modifiers": [
        "public",
        "abstract"
      ]
    },
    "uri": {
      "idUri": "fuse/controls/native/itoggleview/value",
      "href": "fuse/controls/native/itoggleview/value"
    },
    "titles": {
      "pageTitle": "IToggleView.Value Property",
      "navigationTitle": "Value Property",
      "fullTitle": "Fuse.Controls.Native.IToggleView.Value",
      "indexTitle": "Value",
      "fullyQualifiedIndexTitle": "Fuse.Controls.Native.IToggleView.Value"
    },
    "syntax": {
      "uno": "public abstract bool Value { get; }"
    }
  },
  "tableOfContents": {}
}