{
  "entity": {
    "location": {
      "namespaceTitle": "Fuse.Resources",
      "namespaceUri": "fuse/resources",
      "packageName": "Fuse.Elements",
      "packageVersion": "1.11.2"
    },
    "parameters": [],
    "returns": {
      "href": "uno/int2",
      "title": "int2",
      "fullyQualifiedTitle": "int2"
    },
    "id": {
      "id": "fuse/resources/imagesource/pixelsize",
      "parentId": "fuse/resources/imagesource",
      "type": "Property",
      "modifiers": [
        "public",
        "abstract"
      ]
    },
    "uri": {
      "idUri": "fuse/resources/imagesource/pixelsize",
      "href": "fuse/resources/imagesource/pixelsize"
    },
    "titles": {
      "pageTitle": "ImageSource.PixelSize Property",
      "navigationTitle": "PixelSize Property",
      "fullTitle": "Fuse.Resources.ImageSource.PixelSize",
      "indexTitle": "PixelSize",
      "fullyQualifiedIndexTitle": "Fuse.Resources.ImageSource.PixelSize"
    },
    "syntax": {
      "uno": "public abstract int2 PixelSize { get; }"
    }
  },
  "tableOfContents": {}
}