{
  "root": {
    "id": {
      "id": "uno/graphics/utils/text/textshader",
      "parentId": "uno/graphics/utils/text",
      "type": "Class",
      "modifiers": [
        "public",
        "abstract"
      ]
    },
    "uri": {
      "idUri": "uno/graphics/utils/text/textshader",
      "href": "uno/graphics/utils/text/textshader"
    },
    "titles": {
      "indexTitle": "TextShader",
      "fullyQualifiedIndexTitle": "Uno.Graphics.Utils.Text.TextShader"
    }
  },
  "descendants": [
    {
      "id": {
        "id": "uno/graphics/utils/text/spritefontshader",
        "parentId": "uno/graphics/utils/text",
        "type": "Class",
        "modifiers": [
          "public"
        ]
      },
      "uri": {
        "idUri": "uno/graphics/utils/text/spritefontshader",
        "href": "uno/graphics/utils/text/spritefontshader"
      },
      "titles": {
        "indexTitle": "SpriteFontShader",
        "fullyQualifiedIndexTitle": "Uno.Graphics.Utils.Text.SpriteFontShader"
      }
    }
  ]
}