{
  "entity": {
    "location": {
      "namespaceTitle": "Uno",
      "namespaceUri": "uno",
      "packageName": "UnoCore",
      "packageVersion": "1.11.1"
    },
    "parameters": [
      {
        "name": "x",
        "href": "uno/short",
        "title": "short",
        "fullyQualifiedTitle": "short"
      },
      {
        "name": "y",
        "href": "uno/short",
        "title": "short",
        "fullyQualifiedTitle": "short"
      }
    ],
    "id": {
      "id": "uno/short2/_ctor_29cbcb19",
      "parentId": "uno/short2",
      "type": "Constructor",
      "modifiers": [
        "public"
      ]
    },
    "uri": {
      "idUri": "uno/short2/_ctor_29cbcb19",
      "href": "uno/short2/_ctor_29cbcb19"
    },
    "titles": {
      "pageTitle": "short2 Constructor (short, short)",
      "navigationTitle": "short2 Constructor (short, short)",
      "fullTitle": "short2..ctor",
      "indexTitle": "short2(short, short)",
      "fullyQualifiedIndexTitle": "Uno.Short2.short2(short, short)"
    },
    "syntax": {
      "uno": "public Short2(short x, short y) {}"
    }
  },
  "tableOfContents": {}
}