{
  "entity": {
    "location": {
      "namespaceTitle": "Fuse.Triggers.Actions",
      "namespaceUri": "fuse/triggers/actions",
      "packageName": "Fuse.Triggers",
      "packageVersion": "1.11.2"
    },
    "parameters": [
      {
        "name": "flag",
        "href": "fuse/triggers/actions/timelineactionhow",
        "title": "TimelineActionHow",
        "fullyQualifiedTitle": "Fuse.Triggers.Actions.TimelineActionHow"
      }
    ],
    "returns": {
      "href": "uno/bool",
      "title": "bool",
      "fullyQualifiedTitle": "bool"
    },
    "id": {
      "id": "fuse/triggers/actions/timelineactionhow/hasflag_88b366a0",
      "parentId": "fuse/triggers/actions/timelineactionhow",
      "type": "Method",
      "modifiers": [
        "public",
        "intrinsic",
        "generated"
      ]
    },
    "uri": {
      "idUri": "fuse/triggers/actions/timelineactionhow/hasflag_88b366a0",
      "href": "fuse/triggers/actions/timelineactionhow/hasflag_88b366a0"
    },
    "titles": {
      "pageTitle": "TimelineActionHow.HasFlag Method (TimelineActionHow)",
      "navigationTitle": "HasFlag Method (TimelineActionHow)",
      "fullTitle": "Fuse.Triggers.Actions.TimelineActionHow.HasFlag",
      "indexTitle": "HasFlag(TimelineActionHow)",
      "fullyQualifiedIndexTitle": "Fuse.Triggers.Actions.TimelineActionHow.HasFlag(Fuse.Triggers.Actions.TimelineActionHow)"
    },
    "syntax": {
      "uno": "public intrinsic generated bool HasFlag(Fuse.Triggers.Actions.TimelineActionHow flag) {}"
    }
  },
  "tableOfContents": {}
}