{
  "entity": {
    "location": {
      "namespaceTitle": "Fuse.Reactive",
      "namespaceUri": "fuse/reactive",
      "packageName": "Fuse.Reactive.Bindings",
      "packageVersion": "1.11.2"
    },
    "parameters": [],
    "returns": {
      "href": "fuse/reactive/iexpression",
      "title": "IExpression",
      "fullyQualifiedTitle": "Fuse.Reactive.IExpression"
    },
    "id": {
      "id": "fuse/reactive/expressionbinding/key",
      "parentId": "fuse/reactive/expressionbinding",
      "type": "Property",
      "modifiers": [
        "public"
      ]
    },
    "uri": {
      "idUri": "fuse/reactive/expressionbinding/key",
      "href": "fuse/reactive/expressionbinding/key"
    },
    "titles": {
      "pageTitle": "ExpressionBinding.Key Property",
      "navigationTitle": "Key Property",
      "fullTitle": "Fuse.Reactive.ExpressionBinding.Key",
      "indexTitle": "Key",
      "fullyQualifiedIndexTitle": "Fuse.Reactive.ExpressionBinding.Key"
    },
    "syntax": {
      "uno": "public Fuse.Reactive.IExpression Key { get; get; }"
    }
  },
  "tableOfContents": {}
}