{
  "entity": {
    "id": {
      "id": "fuse/controls/native",
      "parentId": "fuse/controls",
      "type": "Namespace",
      "modifiers": []
    },
    "uri": {
      "idUri": "fuse/controls/native",
      "href": "fuse/controls/native"
    },
    "titles": {
      "pageTitle": "Fuse.Controls.Native Namespace",
      "navigationTitle": "Fuse.Controls.Native Namespace",
      "fullTitle": "Fuse.Controls.Native",
      "indexTitle": "Fuse.Controls.Native",
      "fullyQualifiedIndexTitle": "Fuse.Controls.Native"
    },
    "syntax": {
      "uno": "namespace Native {}"
    }
  },
  "tableOfContents": {
    "namespaces": [
      {
        "items": [
          {
            "id": {
              "id": "fuse/controls/native/android",
              "parentId": "fuse/controls/native",
              "type": "Namespace",
              "modifiers": []
            },
            "uri": {
              "idUri": "fuse/controls/native/android",
              "href": "fuse/controls/native/android"
            },
            "titles": {
              "indexTitle": "Fuse.Controls.Native.Android",
              "fullyQualifiedIndexTitle": "Fuse.Controls.Native.Android"
            }
          },
          {
            "id": {
              "id": "fuse/controls/native/ios",
              "parentId": "fuse/controls/native",
              "type": "Namespace",
              "modifiers": []
            },
            "uri": {
              "idUri": "fuse/controls/native/ios",
              "href": "fuse/controls/native/ios"
            },
            "titles": {
              "indexTitle": "Fuse.Controls.Native.iOS",
              "fullyQualifiedIndexTitle": "Fuse.Controls.Native.iOS"
            }
          }
        ]
      }
    ],
    "uxClasses": [
      {
        "items": [
          {
            "id": {
              "id": "fuse/controls/native/viewhandle",
              "parentId": "fuse/controls/native",
              "type": "UxClass",
              "modifiers": [
                "public"
              ]
            },
            "uri": {
              "idUri": "fuse/controls/native/viewhandle",
              "href": "fuse/controls/native/viewhandle"
            },
            "titles": {
              "indexTitle": "ViewHandle",
              "fullyQualifiedIndexTitle": "Fuse.Controls.Native.ViewHandle"
            }
          }
        ]
      }
    ],
    "enums": [
      {
        "items": [
          {
            "id": {
              "id": "fuse/controls/native/offscreenrendering",
              "parentId": "fuse/controls/native",
              "type": "Enum",
              "modifiers": [
                "public"
              ]
            },
            "uri": {
              "idUri": "fuse/controls/native/offscreenrendering",
              "href": "fuse/controls/native/offscreenrendering"
            },
            "titles": {
              "indexTitle": "OffscreenRendering",
              "fullyQualifiedIndexTitle": "Fuse.Controls.Native.OffscreenRendering"
            }
          }
        ]
      }
    ],
    "interfaces": [
      {
        "items": [
          {
            "id": {
              "id": "fuse/controls/native/icircleview",
              "parentId": "fuse/controls/native",
              "type": "Interface",
              "modifiers": [
                "public",
                "abstract"
              ]
            },
            "uri": {
              "idUri": "fuse/controls/native/icircleview",
              "href": "fuse/controls/native/icircleview"
            },
            "titles": {
              "indexTitle": "ICircleView",
              "fullyQualifiedIndexTitle": "Fuse.Controls.Native.ICircleView"
            }
          },
          {
            "id": {
              "id": "fuse/controls/native/igraphicsview",
              "parentId": "fuse/controls/native",
              "type": "Interface",
              "modifiers": [
                "public",
                "abstract"
              ]
            },
            "uri": {
              "idUri": "fuse/controls/native/igraphicsview",
              "href": "fuse/controls/native/igraphicsview"
            },
            "titles": {
              "indexTitle": "IGraphicsView",
              "fullyQualifiedIndexTitle": "Fuse.Controls.Native.IGraphicsView"
            }
          },
          {
            "id": {
              "id": "fuse/controls/native/iimageview",
              "parentId": "fuse/controls/native",
              "type": "Interface",
              "modifiers": [
                "public",
                "abstract"
              ]
            },
            "uri": {
              "idUri": "fuse/controls/native/iimageview",
              "href": "fuse/controls/native/iimageview"
            },
            "titles": {
              "indexTitle": "IImageView",
              "fullyQualifiedIndexTitle": "Fuse.Controls.Native.IImageView"
            }
          },
          {
            "id": {
              "id": "fuse/controls/native/ilabelview",
              "parentId": "fuse/controls/native",
              "type": "Interface",
              "modifiers": [
                "public",
                "abstract"
              ]
            },
            "uri": {
              "idUri": "fuse/controls/native/ilabelview",
              "href": "fuse/controls/native/ilabelview"
            },
            "titles": {
              "indexTitle": "ILabelView",
              "fullyQualifiedIndexTitle": "Fuse.Controls.Native.ILabelView"
            }
          },
          {
            "id": {
              "id": "fuse/controls/native/ileafview",
              "parentId": "fuse/controls/native",
              "type": "Interface",
              "modifiers": [
                "public",
                "abstract"
              ]
            },
            "uri": {
              "idUri": "fuse/controls/native/ileafview",
              "href": "fuse/controls/native/ileafview"
            },
            "titles": {
              "indexTitle": "ILeafView",
              "fullyQualifiedIndexTitle": "Fuse.Controls.Native.ILeafView"
            }
          },
          {
            "id": {
              "id": "fuse/controls/native/inativeviewrenderer",
              "parentId": "fuse/controls/native",
              "type": "Interface",
              "modifiers": [
                "public",
                "abstract"
              ]
            },
            "uri": {
              "idUri": "fuse/controls/native/inativeviewrenderer",
              "href": "fuse/controls/native/inativeviewrenderer"
            },
            "titles": {
              "indexTitle": "INativeViewRenderer",
              "fullyQualifiedIndexTitle": "Fuse.Controls.Native.INativeViewRenderer"
            }
          },
          {
            "id": {
              "id": "fuse/controls/native/ioffscreenrenderer",
              "parentId": "fuse/controls/native",
              "type": "Interface",
              "modifiers": [
                "public",
                "abstract"
              ]
            },
            "uri": {
              "idUri": "fuse/controls/native/ioffscreenrenderer",
              "href": "fuse/controls/native/ioffscreenrenderer"
            },
            "titles": {
              "indexTitle": "IOffscreenRenderer",
              "fullyQualifiedIndexTitle": "Fuse.Controls.Native.IOffscreenRenderer"
            }
          },
          {
            "id": {
              "id": "fuse/controls/native/ioffscreenrendererhost",
              "parentId": "fuse/controls/native",
              "type": "Interface",
              "modifiers": [
                "public",
                "abstract"
              ]
            },
            "uri": {
              "idUri": "fuse/controls/native/ioffscreenrendererhost",
              "href": "fuse/controls/native/ioffscreenrendererhost"
            },
            "titles": {
              "indexTitle": "IOffscreenRendererHost",
              "fullyQualifiedIndexTitle": "Fuse.Controls.Native.IOffscreenRendererHost"
            }
          },
          {
            "id": {
              "id": "fuse/controls/native/irangeview",
              "parentId": "fuse/controls/native",
              "type": "Interface",
              "modifiers": [
                "public",
                "abstract"
              ]
            },
            "uri": {
              "idUri": "fuse/controls/native/irangeview",
              "href": "fuse/controls/native/irangeview"
            },
            "titles": {
              "indexTitle": "IRangeView",
              "fullyQualifiedIndexTitle": "Fuse.Controls.Native.IRangeView"
            }
          },
          {
            "id": {
              "id": "fuse/controls/native/irangeviewhost",
              "parentId": "fuse/controls/native",
              "type": "Interface",
              "modifiers": [
                "public",
                "abstract"
              ]
            },
            "uri": {
              "idUri": "fuse/controls/native/irangeviewhost",
              "href": "fuse/controls/native/irangeviewhost"
            },
            "titles": {
              "indexTitle": "IRangeViewHost",
              "fullyQualifiedIndexTitle": "Fuse.Controls.Native.IRangeViewHost"
            }
          },
          {
            "id": {
              "id": "fuse/controls/native/irectangleview",
              "parentId": "fuse/controls/native",
              "type": "Interface",
              "modifiers": [
                "public",
                "abstract"
              ]
            },
            "uri": {
              "idUri": "fuse/controls/native/irectangleview",
              "href": "fuse/controls/native/irectangleview"
            },
            "titles": {
              "indexTitle": "IRectangleView",
              "fullyQualifiedIndexTitle": "Fuse.Controls.Native.IRectangleView"
            }
          },
          {
            "id": {
              "id": "fuse/controls/native/iscrollview",
              "parentId": "fuse/controls/native",
              "type": "Interface",
              "modifiers": [
                "public",
                "abstract"
              ]
            },
            "uri": {
              "idUri": "fuse/controls/native/iscrollview",
              "href": "fuse/controls/native/iscrollview"
            },
            "titles": {
              "indexTitle": "IScrollView",
              "fullyQualifiedIndexTitle": "Fuse.Controls.Native.IScrollView"
            }
          },
          {
            "id": {
              "id": "fuse/controls/native/iscrollviewhost",
              "parentId": "fuse/controls/native",
              "type": "Interface",
              "modifiers": [
                "public",
                "abstract"
              ]
            },
            "uri": {
              "idUri": "fuse/controls/native/iscrollviewhost",
              "href": "fuse/controls/native/iscrollviewhost"
            },
            "titles": {
              "indexTitle": "IScrollViewHost",
              "fullyQualifiedIndexTitle": "Fuse.Controls.Native.IScrollViewHost"
            }
          },
          {
            "id": {
              "id": "fuse/controls/native/ishapeview",
              "parentId": "fuse/controls/native",
              "type": "Interface",
              "modifiers": [
                "public",
                "abstract"
              ]
            },
            "uri": {
              "idUri": "fuse/controls/native/ishapeview",
              "href": "fuse/controls/native/ishapeview"
            },
            "titles": {
              "indexTitle": "IShapeView",
              "fullyQualifiedIndexTitle": "Fuse.Controls.Native.IShapeView"
            }
          },
          {
            "id": {
              "id": "fuse/controls/native/itextedit",
              "parentId": "fuse/controls/native",
              "type": "Interface",
              "modifiers": [
                "public",
                "abstract"
              ]
            },
            "uri": {
              "idUri": "fuse/controls/native/itextedit",
              "href": "fuse/controls/native/itextedit"
            },
            "titles": {
              "indexTitle": "ITextEdit",
              "fullyQualifiedIndexTitle": "Fuse.Controls.Native.ITextEdit"
            }
          },
          {
            "id": {
              "id": "fuse/controls/native/itextedithost",
              "parentId": "fuse/controls/native",
              "type": "Interface",
              "modifiers": [
                "public",
                "abstract"
              ]
            },
            "uri": {
              "idUri": "fuse/controls/native/itextedithost",
              "href": "fuse/controls/native/itextedithost"
            },
            "titles": {
              "indexTitle": "ITextEditHost",
              "fullyQualifiedIndexTitle": "Fuse.Controls.Native.ITextEditHost"
            }
          },
          {
            "id": {
              "id": "fuse/controls/native/itextview",
              "parentId": "fuse/controls/native",
              "type": "Interface",
              "modifiers": [
                "public",
                "abstract"
              ]
            },
            "uri": {
              "idUri": "fuse/controls/native/itextview",
              "href": "fuse/controls/native/itextview"
            },
            "titles": {
              "indexTitle": "ITextView",
              "fullyQualifiedIndexTitle": "Fuse.Controls.Native.ITextView"
            }
          },
          {
            "id": {
              "id": "fuse/controls/native/itoggleview",
              "parentId": "fuse/controls/native",
              "type": "Interface",
              "modifiers": [
                "public",
                "abstract"
              ]
            },
            "uri": {
              "idUri": "fuse/controls/native/itoggleview",
              "href": "fuse/controls/native/itoggleview"
            },
            "titles": {
              "indexTitle": "IToggleView",
              "fullyQualifiedIndexTitle": "Fuse.Controls.Native.IToggleView"
            }
          },
          {
            "id": {
              "id": "fuse/controls/native/itoggleviewhost",
              "parentId": "fuse/controls/native",
              "type": "Interface",
              "modifiers": [
                "public",
                "abstract"
              ]
            },
            "uri": {
              "idUri": "fuse/controls/native/itoggleviewhost",
              "href": "fuse/controls/native/itoggleviewhost"
            },
            "titles": {
              "indexTitle": "IToggleViewHost",
              "fullyQualifiedIndexTitle": "Fuse.Controls.Native.IToggleViewHost"
            }
          },
          {
            "id": {
              "id": "fuse/controls/native/iview",
              "parentId": "fuse/controls/native",
              "type": "Interface",
              "modifiers": [
                "public",
                "abstract"
              ]
            },
            "uri": {
              "idUri": "fuse/controls/native/iview",
              "href": "fuse/controls/native/iview"
            },
            "titles": {
              "indexTitle": "IView",
              "fullyQualifiedIndexTitle": "Fuse.Controls.Native.IView"
            }
          },
          {
            "id": {
              "id": "fuse/controls/native/iviewgroup",
              "parentId": "fuse/controls/native",
              "type": "Interface",
              "modifiers": [
                "public",
                "abstract"
              ]
            },
            "uri": {
              "idUri": "fuse/controls/native/iviewgroup",
              "href": "fuse/controls/native/iviewgroup"
            },
            "titles": {
              "indexTitle": "IViewGroup",
              "fullyQualifiedIndexTitle": "Fuse.Controls.Native.IViewGroup"
            }
          },
          {
            "id": {
              "id": "fuse/controls/native/iviewhost",
              "parentId": "fuse/controls/native",
              "type": "Interface",
              "modifiers": [
                "public",
                "abstract"
              ]
            },
            "uri": {
              "idUri": "fuse/controls/native/iviewhost",
              "href": "fuse/controls/native/iviewhost"
            },
            "titles": {
              "indexTitle": "IViewHost",
              "fullyQualifiedIndexTitle": "Fuse.Controls.Native.IViewHost"
            }
          }
        ]
      }
    ]
  }
}