{
  "entity": {
    "base": {
      "id": {
        "id": "uno/object",
        "parentId": "uno",
        "type": "Class",
        "modifiers": [
          "public",
          "intrinsic"
        ]
      },
      "uri": {
        "idUri": "uno/object",
        "href": "uno/object"
      },
      "titles": {
        "indexTitle": "object",
        "fullyQualifiedIndexTitle": "object"
      }
    },
    "location": {
      "namespaceTitle": "Fuse.Motion.Simulation",
      "namespaceUri": "fuse/motion/simulation",
      "packageName": "Fuse.Motion",
      "packageVersion": "1.11.2"
    },
    "inheritance": {
      "root": {
        "uri": "uno/object",
        "title": "object",
        "children": [
          {
            "uri": "fuse/motion/simulation/pointervelocity_1",
            "title": "Fuse.Motion.Simulation.PointerVelocity<T>",
            "children": [],
            "isCurrent": true
          }
        ],
        "isAncestor": true
      },
      "hasInheritance": true
    },
    "uxProperties": {
      "uxNamespaceTitle": "Fuse",
      "uxNamespaceUri": "fuse",
      "uxName": "Motion.Simulation.PointerVelocity"
    },
    "id": {
      "id": "fuse/motion/simulation/pointervelocity_1",
      "parentId": "fuse/motion/simulation",
      "type": "UxClass",
      "modifiers": [
        "public"
      ]
    },
    "uri": {
      "idUri": "fuse/motion/simulation/pointervelocity_1",
      "href": "fuse/motion/simulation/pointervelocity_1"
    },
    "titles": {
      "pageTitle": "PointerVelocity<T> Class",
      "navigationTitle": "PointerVelocity<T> Class",
      "fullTitle": "Fuse.Motion.Simulation.PointerVelocity",
      "indexTitle": "PointerVelocity<T>",
      "fullyQualifiedIndexTitle": "Fuse.Motion.Simulation.PointerVelocity<T>"
    },
    "syntax": {
      "uno": "public class PointerVelocity<T> {}",
      "ux": "<Motion.Simulation.PointerVelocity />"
    },
    "comment": {
      "brief": "Determines the appropriate velocity from pointerDown/Move/Release events.",
      "full": "Determines the appropriate velocity from pointerDown/Move/Release events."
    }
  },
  "tableOfContents": {
    "uxProperties": [
      {
        "declaredIn": {
          "id": {
            "id": "fuse/motion/simulation/pointervelocity_1",
            "parentId": "fuse/motion/simulation",
            "type": "UxClass",
            "modifiers": [
              "public"
            ]
          },
          "uri": {
            "idUri": "fuse/motion/simulation/pointervelocity_1",
            "href": "fuse/motion/simulation/pointervelocity_1"
          },
          "titles": {
            "indexTitle": "PointerVelocity<T>",
            "fullyQualifiedIndexTitle": "Fuse.Motion.Simulation.PointerVelocity<T>"
          }
        },
        "items": [
          {
            "returns": {
              "isVirtual": true,
              "title": "T",
              "fullyQualifiedTitle": "Fuse.Motion.Simulation.T"
            },
            "id": {
              "id": "fuse/motion/simulation/pointervelocity_1/currentvelocity",
              "parentId": "fuse/motion/simulation/pointervelocity_1",
              "type": "UxProperty",
              "modifiers": [
                "public"
              ]
            },
            "uri": {
              "idUri": "fuse/motion/simulation/pointervelocity_1/currentvelocity",
              "href": "fuse/motion/simulation/pointervelocity_1/currentvelocity"
            },
            "titles": {
              "indexTitle": "CurrentVelocity",
              "fullyQualifiedIndexTitle": "Fuse.Motion.Simulation.PointerVelocity.CurrentVelocity"
            }
          },
          {
            "returns": {
              "href": "uno/float",
              "title": "float",
              "fullyQualifiedTitle": "float"
            },
            "id": {
              "id": "fuse/motion/simulation/pointervelocity_1/period",
              "parentId": "fuse/motion/simulation/pointervelocity_1",
              "type": "UxProperty",
              "modifiers": [
                "public"
              ]
            },
            "uri": {
              "idUri": "fuse/motion/simulation/pointervelocity_1/period",
              "href": "fuse/motion/simulation/pointervelocity_1/period"
            },
            "titles": {
              "indexTitle": "Period",
              "fullyQualifiedIndexTitle": "Fuse.Motion.Simulation.PointerVelocity.Period"
            }
          }
        ]
      }
    ],
    "attachedUxProperties": [
      {
        "items": [
          {
            "comment": {
              "brief": "The `ux:Global` attribute creates a global resource that is accessible everywhere in UX markup.",
              "full": "The `ux:Global` attribute creates a global resource that is accessible everywhere in UX markup.\n\nSee @Resources for more information.\n\nThe `ux:Global` attribute on an UX element creates a single object (singleton) that is globally available.\nUsing this attribute will prevent the object from being inserted by default the object at its defined location\nin the UX tree."
            },
            "returns": {
              "href": "uno/string",
              "title": "string",
              "fullyQualifiedTitle": "string"
            },
            "parameters": [
              {
                "name": "obj",
                "href": "uno/object",
                "title": "object",
                "fullyQualifiedTitle": "object"
              },
              {
                "name": "key",
                "href": "uno/string",
                "title": "string",
                "fullyQualifiedTitle": "string"
              }
            ],
            "id": {
              "id": "fuse/motion/simulation/pointervelocity_1/resource_globalkey_setglobalkey_4c3ac72d",
              "parentId": "fuse/motion/simulation/pointervelocity_1",
              "type": "AttachedUxProperty",
              "modifiers": []
            },
            "uri": {
              "idUri": "fuse/motion/simulation/pointervelocity_1/resource_globalkey_setglobalkey_4c3ac72d",
              "href": "uno/ux/resource/setglobalkey_4c3ac72d",
              "isVirtual": true
            },
            "titles": {
              "indexTitle": "Resource.GlobalKey",
              "fullyQualifiedIndexTitle": "Resource.GlobalKey"
            }
          }
        ]
      }
    ],
    "constructors": [
      {
        "declaredIn": {
          "id": {
            "id": "fuse/motion/simulation/pointervelocity_1",
            "parentId": "fuse/motion/simulation",
            "type": "UxClass",
            "modifiers": [
              "public"
            ]
          },
          "uri": {
            "idUri": "fuse/motion/simulation/pointervelocity_1",
            "href": "fuse/motion/simulation/pointervelocity_1"
          },
          "titles": {
            "indexTitle": "PointerVelocity<T>",
            "fullyQualifiedIndexTitle": "Fuse.Motion.Simulation.PointerVelocity<T>"
          }
        },
        "items": [
          {
            "comment": {
              "brief": "Creates a new PointerVelocity<T>",
              "full": "Creates a new PointerVelocity<T>"
            },
            "id": {
              "id": "fuse/motion/simulation/pointervelocity_1/_ctor",
              "parentId": "fuse/motion/simulation/pointervelocity_1",
              "type": "Constructor",
              "modifiers": [
                "public",
                "generated"
              ]
            },
            "uri": {
              "idUri": "fuse/motion/simulation/pointervelocity_1/_ctor",
              "href": "fuse/motion/simulation/pointervelocity_1/_ctor"
            },
            "titles": {
              "indexTitle": "PointerVelocity",
              "fullyQualifiedIndexTitle": "Fuse.Motion.Simulation.PointerVelocity.PointerVelocity"
            }
          }
        ]
      }
    ],
    "properties": [
      {
        "declaredIn": {
          "id": {
            "id": "fuse/motion/simulation/pointervelocity_1",
            "parentId": "fuse/motion/simulation",
            "type": "UxClass",
            "modifiers": [
              "public"
            ]
          },
          "uri": {
            "idUri": "fuse/motion/simulation/pointervelocity_1",
            "href": "fuse/motion/simulation/pointervelocity_1"
          },
          "titles": {
            "indexTitle": "PointerVelocity<T>",
            "fullyQualifiedIndexTitle": "Fuse.Motion.Simulation.PointerVelocity<T>"
          }
        },
        "items": [
          {
            "returns": {
              "isVirtual": true,
              "title": "T",
              "fullyQualifiedTitle": "Fuse.Motion.Simulation.T"
            },
            "id": {
              "id": "fuse/motion/simulation/pointervelocity_1/averagevelocity",
              "parentId": "fuse/motion/simulation/pointervelocity_1",
              "type": "Property",
              "modifiers": [
                "public"
              ]
            },
            "uri": {
              "idUri": "fuse/motion/simulation/pointervelocity_1/averagevelocity",
              "href": "fuse/motion/simulation/pointervelocity_1/averagevelocity"
            },
            "titles": {
              "indexTitle": "AverageVelocity",
              "fullyQualifiedIndexTitle": "Fuse.Motion.Simulation.PointerVelocity.AverageVelocity"
            }
          },
          {
            "returns": {
              "href": "uno/double",
              "title": "double",
              "fullyQualifiedTitle": "double"
            },
            "id": {
              "id": "fuse/motion/simulation/pointervelocity_1/totaldistance",
              "parentId": "fuse/motion/simulation/pointervelocity_1",
              "type": "Property",
              "modifiers": [
                "public"
              ]
            },
            "uri": {
              "idUri": "fuse/motion/simulation/pointervelocity_1/totaldistance",
              "href": "fuse/motion/simulation/pointervelocity_1/totaldistance"
            },
            "titles": {
              "indexTitle": "TotalDistance",
              "fullyQualifiedIndexTitle": "Fuse.Motion.Simulation.PointerVelocity.TotalDistance"
            }
          }
        ]
      }
    ],
    "methods": [
      {
        "declaredIn": {
          "id": {
            "id": "fuse/motion/simulation/pointervelocity_1",
            "parentId": "fuse/motion/simulation",
            "type": "UxClass",
            "modifiers": [
              "public"
            ]
          },
          "uri": {
            "idUri": "fuse/motion/simulation/pointervelocity_1",
            "href": "fuse/motion/simulation/pointervelocity_1"
          },
          "titles": {
            "indexTitle": "PointerVelocity<T>",
            "fullyQualifiedIndexTitle": "Fuse.Motion.Simulation.PointerVelocity<T>"
          }
        },
        "items": [
          {
            "parameters": [
              {
                "name": "location",
                "isVirtual": true,
                "title": "T",
                "fullyQualifiedTitle": "Fuse.Motion.Simulation.T"
              },
              {
                "name": "elapsed",
                "href": "uno/double",
                "title": "double",
                "fullyQualifiedTitle": "double"
              },
              {
                "name": "flags",
                "href": "fuse/motion/simulation/sampleflags",
                "title": "SampleFlags",
                "fullyQualifiedTitle": "Fuse.Motion.Simulation.SampleFlags"
              }
            ],
            "id": {
              "id": "fuse/motion/simulation/pointervelocity_1/addsample_ab6e626a",
              "parentId": "fuse/motion/simulation/pointervelocity_1",
              "type": "Method",
              "modifiers": [
                "public"
              ]
            },
            "uri": {
              "idUri": "fuse/motion/simulation/pointervelocity_1/addsample_ab6e626a",
              "href": "fuse/motion/simulation/pointervelocity_1/addsample_ab6e626a"
            },
            "titles": {
              "indexTitle": "AddSample(T, double, SampleFlags)",
              "fullyQualifiedIndexTitle": "Fuse.Motion.Simulation.PointerVelocity.AddSample(T, double, Fuse.Motion.Simulation.SampleFlags)"
            }
          },
          {
            "parameters": [
              {
                "name": "location",
                "isVirtual": true,
                "title": "T",
                "fullyQualifiedTitle": "Fuse.Motion.Simulation.T"
              },
              {
                "name": "timestamp",
                "href": "uno/double",
                "title": "double",
                "fullyQualifiedTitle": "double"
              },
              {
                "name": "flags",
                "href": "fuse/motion/simulation/sampleflags",
                "title": "SampleFlags",
                "fullyQualifiedTitle": "Fuse.Motion.Simulation.SampleFlags"
              }
            ],
            "id": {
              "id": "fuse/motion/simulation/pointervelocity_1/addsampletime_ab6e626a",
              "parentId": "fuse/motion/simulation/pointervelocity_1",
              "type": "Method",
              "modifiers": [
                "public"
              ]
            },
            "uri": {
              "idUri": "fuse/motion/simulation/pointervelocity_1/addsampletime_ab6e626a",
              "href": "fuse/motion/simulation/pointervelocity_1/addsampletime_ab6e626a"
            },
            "titles": {
              "indexTitle": "AddSampleTime(T, double, SampleFlags)",
              "fullyQualifiedIndexTitle": "Fuse.Motion.Simulation.PointerVelocity.AddSampleTime(T, double, Fuse.Motion.Simulation.SampleFlags)"
            }
          },
          {
            "parameters": [
              {
                "name": "location0",
                "isVirtual": true,
                "title": "T",
                "fullyQualifiedTitle": "Fuse.Motion.Simulation.T"
              }
            ],
            "id": {
              "id": "fuse/motion/simulation/pointervelocity_1/reset_be047a60",
              "parentId": "fuse/motion/simulation/pointervelocity_1",
              "type": "Method",
              "modifiers": [
                "public"
              ]
            },
            "uri": {
              "idUri": "fuse/motion/simulation/pointervelocity_1/reset_be047a60",
              "href": "fuse/motion/simulation/pointervelocity_1/reset_be047a60"
            },
            "titles": {
              "indexTitle": "Reset(T)",
              "fullyQualifiedIndexTitle": "Fuse.Motion.Simulation.PointerVelocity.Reset(T)"
            }
          },
          {
            "parameters": [
              {
                "name": "location0",
                "isVirtual": true,
                "title": "T",
                "fullyQualifiedTitle": "Fuse.Motion.Simulation.T"
              },
              {
                "name": "velocity0",
                "isVirtual": true,
                "title": "T",
                "fullyQualifiedTitle": "Fuse.Motion.Simulation.T"
              },
              {
                "name": "currentTime",
                "href": "uno/double",
                "title": "double",
                "fullyQualifiedTitle": "double"
              }
            ],
            "id": {
              "id": "fuse/motion/simulation/pointervelocity_1/reset_447f02ba",
              "parentId": "fuse/motion/simulation/pointervelocity_1",
              "type": "Method",
              "modifiers": [
                "public"
              ]
            },
            "uri": {
              "idUri": "fuse/motion/simulation/pointervelocity_1/reset_447f02ba",
              "href": "fuse/motion/simulation/pointervelocity_1/reset_447f02ba"
            },
            "titles": {
              "indexTitle": "Reset(T, T, double)",
              "fullyQualifiedIndexTitle": "Fuse.Motion.Simulation.PointerVelocity.Reset(T, T, double)"
            }
          }
        ]
      },
      {
        "declaredIn": {
          "id": {
            "id": "uno/object",
            "parentId": "uno",
            "type": "Class",
            "modifiers": [
              "public",
              "intrinsic"
            ]
          },
          "uri": {
            "idUri": "uno/object",
            "href": "uno/object"
          },
          "titles": {
            "indexTitle": "object",
            "fullyQualifiedIndexTitle": "object"
          }
        },
        "items": [
          {
            "returns": {
              "href": "uno/bool",
              "title": "bool",
              "fullyQualifiedTitle": "bool"
            },
            "parameters": [
              {
                "name": "o",
                "href": "uno/object",
                "title": "object",
                "fullyQualifiedTitle": "object"
              }
            ],
            "id": {
              "id": "fuse/motion/simulation/pointervelocity_1/equals_a09c80e3",
              "parentId": "fuse/motion/simulation/pointervelocity_1",
              "type": "Method",
              "modifiers": [
                "public",
                "virtual"
              ]
            },
            "uri": {
              "idUri": "fuse/motion/simulation/pointervelocity_1/equals_a09c80e3",
              "href": "uno/object/equals_a09c80e3",
              "isVirtual": true
            },
            "titles": {
              "indexTitle": "Equals(object)",
              "fullyQualifiedIndexTitle": "Uno.Object.Equals(object)"
            }
          },
          {
            "returns": {
              "href": "uno/int",
              "title": "int",
              "fullyQualifiedTitle": "int"
            },
            "id": {
              "id": "fuse/motion/simulation/pointervelocity_1/gethashcode",
              "parentId": "fuse/motion/simulation/pointervelocity_1",
              "type": "Method",
              "modifiers": [
                "public",
                "virtual"
              ]
            },
            "uri": {
              "idUri": "fuse/motion/simulation/pointervelocity_1/gethashcode",
              "href": "uno/object/gethashcode",
              "isVirtual": true
            },
            "titles": {
              "indexTitle": "GetHashCode",
              "fullyQualifiedIndexTitle": "Uno.Object.GetHashCode"
            }
          },
          {
            "returns": {
              "href": "uno/type",
              "title": "Type",
              "fullyQualifiedTitle": "Uno.Type"
            },
            "id": {
              "id": "fuse/motion/simulation/pointervelocity_1/gettype",
              "parentId": "fuse/motion/simulation/pointervelocity_1",
              "type": "Method",
              "modifiers": [
                "public"
              ]
            },
            "uri": {
              "idUri": "fuse/motion/simulation/pointervelocity_1/gettype",
              "href": "uno/object/gettype",
              "isVirtual": true
            },
            "titles": {
              "indexTitle": "GetType",
              "fullyQualifiedIndexTitle": "Uno.Object.GetType"
            }
          },
          {
            "returns": {
              "href": "uno/string",
              "title": "string",
              "fullyQualifiedTitle": "string"
            },
            "id": {
              "id": "fuse/motion/simulation/pointervelocity_1/tostring",
              "parentId": "fuse/motion/simulation/pointervelocity_1",
              "type": "Method",
              "modifiers": [
                "public",
                "virtual"
              ]
            },
            "uri": {
              "idUri": "fuse/motion/simulation/pointervelocity_1/tostring",
              "href": "uno/object/tostring",
              "isVirtual": true
            },
            "titles": {
              "indexTitle": "ToString",
              "fullyQualifiedIndexTitle": "Uno.Object.ToString"
            }
          }
        ]
      }
    ]
  }
}