{
  "entity": {
    "location": {
      "namespaceTitle": "Fuse.Drawing",
      "namespaceUri": "fuse/drawing",
      "packageName": "Fuse.Drawing",
      "packageVersion": "1.11.2"
    },
    "parameters": [],
    "id": {
      "id": "fuse/drawing/stroke/_ctor",
      "parentId": "fuse/drawing/stroke",
      "type": "Constructor",
      "modifiers": [
        "public"
      ]
    },
    "uri": {
      "idUri": "fuse/drawing/stroke/_ctor",
      "href": "fuse/drawing/stroke/_ctor"
    },
    "titles": {
      "pageTitle": "Stroke Constructor",
      "navigationTitle": "Stroke Constructor",
      "fullTitle": "Fuse.Drawing.Stroke..ctor",
      "indexTitle": "Stroke",
      "fullyQualifiedIndexTitle": "Fuse.Drawing.Stroke.Stroke"
    },
    "syntax": {
      "uno": "public Stroke() {}"
    }
  },
  "tableOfContents": {}
}